seavoice_sdk_beta/__init__.py
seavoice_sdk_beta/commands.py
seavoice_sdk_beta/events.py
seavoice_sdk_beta/exceptions.py
seavoice_sdk_beta/logger.py
seavoice_sdk_beta/speech_to_text.py
seavoice_sdk_beta/text_to_speech.py
seavoice_sdk_beta/tnitn.py
seavoice_sdk_beta/utils.py
seavoice_sdk_test-2.5.3.dist-info/LICENSE
seavoice_sdk_test-2.5.3.dist-info/METADATA
seavoice_sdk_test-2.5.3.dist-info/WHEEL
seavoice_sdk_test-2.5.3.dist-info/top_level.txt
seavoice_sdk_test-2.5.3.dist-info/RECORD
