Metadata-Version: 2.1
Name: seavoice-sdk-test
Version: 2.5.3
Summary: SeaVoice SDK: Client for Seasalt speech recognition and speech synthesis.
Author-email: "Seasalt.ai" <info@seasalt.ai>
Classifier: Programming Language :: Python :: 3
Classifier: License :: OSI Approved :: MIT License
Classifier: Operating System :: OS Independent
Requires-Python: >=3.8
License-File: LICENSE
Requires-Dist: websockets >=10.3
Requires-Dist: typing-extensions >=4.6.1
Provides-Extra: build
Requires-Dist: twine ==4.0.2 ; extra == 'build'
Requires-Dist: build ==1.0.3 ; extra == 'build'
Provides-Extra: dev
Requires-Dist: black ==23.3.0 ; extra == 'dev'
Requires-Dist: isort ==5.12.0 ; extra == 'dev'
Requires-Dist: pyright ==1.1.314 ; extra == 'dev'
Provides-Extra: test
Requires-Dist: pytest ; extra == 'test'
